sheetfu/__init__.py
sheetfu/client.py
sheetfu/exceptions.py
sheetfu/helpers.py
sheetfu/model.py
sheetfu/parsers.py
sheetfu/service.py
sheetfu/modules/__init__.py
sheetfu/modules/table.py
sheetfu/modules/table_selector.py
sheetfu-1.6.1.dist-info/AUTHORS
sheetfu-1.6.1.dist-info/LICENSE
sheetfu-1.6.1.dist-info/METADATA
sheetfu-1.6.1.dist-info/WHEEL
sheetfu-1.6.1.dist-info/top_level.txt
sheetfu-1.6.1.dist-info/RECORD
